.pre-commit-config.yaml
CLA.md
CONTRIBUTING.md
LICENSE
MANIFEST.in
Makefile
README.md
pyproject.toml
pytest.ini
setup.cfg
setup.py
tox.ini
versioneer.py
conda/recipes/meta.yaml
merlin/datasets/__init__.py
merlin/datasets/synthetic.py
merlin/datasets/advertising/__init__.py
merlin/datasets/advertising/criteo/__init__.py
merlin/datasets/advertising/criteo/dataset.py
merlin/datasets/advertising/criteo/transformed/__init__.py
merlin/datasets/advertising/criteo/transformed/schema.pbtxt
merlin/datasets/ecommerce/__init__.py
merlin/datasets/ecommerce/aliccp/__init__.py
merlin/datasets/ecommerce/aliccp/dataset.py
merlin/datasets/ecommerce/aliccp/raw/__init__.py
merlin/datasets/ecommerce/aliccp/raw/schema.pbtxt
merlin/datasets/ecommerce/aliccp/transformed/__init__.py
merlin/datasets/ecommerce/aliccp/transformed/schema.pbtxt
merlin/datasets/ecommerce/booking/__init__.py
merlin/datasets/ecommerce/booking/dataset.py
merlin/datasets/ecommerce/booking/raw/__init__.py
merlin/datasets/ecommerce/booking/raw/schema.pbtxt
merlin/datasets/ecommerce/booking/transformed/__init__.py
merlin/datasets/ecommerce/booking/transformed/schema.pbtxt
merlin/datasets/ecommerce/dressipi/__init__.py
merlin/datasets/ecommerce/dressipi/dataset.py
merlin/datasets/ecommerce/dressipi/preprocessed/__init__.py
merlin/datasets/ecommerce/dressipi/preprocessed/schema.pbtxt
merlin/datasets/ecommerce/large/__init__.py
merlin/datasets/ecommerce/large/schema.json
merlin/datasets/ecommerce/sigir/__init__.py
merlin/datasets/ecommerce/sigir/browsing_train/__init__.py
merlin/datasets/ecommerce/sigir/browsing_train/schema.json
merlin/datasets/ecommerce/sigir/sku_information/__init__.py
merlin/datasets/ecommerce/sigir/sku_information/schema.json
merlin/datasets/ecommerce/small/__init__.py
merlin/datasets/ecommerce/small/schema.json
merlin/datasets/ecommerce/transactions/__init__.py
merlin/datasets/ecommerce/transactions/schema.pbtxt
merlin/datasets/entertainment/__init__.py
merlin_models.egg-info/PKG-INFO
merlin_models.egg-info/SOURCES.txt
merlin_models.egg-info/dependency_links.txt
merlin_models.egg-info/requires.txt
merlin_models.egg-info/top_level.txt
