Metadata-Version: 2.1
Name: merlin-models
Version: 23.12.0
Summary: Merlin recommender system models
Home-page: https://github.com/NVIDIA-Merlin/models
Author: NVIDIA Corporation
License: Apache 2.0
Platform: UNKNOWN
Classifier: Development Status :: 4 - Beta
Classifier: Programming Language :: Python :: 3
Classifier: Intended Audience :: Developers
Classifier: License :: OSI Approved :: Apache Software License
Classifier: Topic :: Software Development :: Libraries
Classifier: Topic :: Scientific/Engineering
Requires-Python: >=3.8
Provides-Extra: base
Provides-Extra: tensorflow
Provides-Extra: pytorch
Provides-Extra: lightfm
Provides-Extra: implicit
Provides-Extra: xgboost
Provides-Extra: transformers
Provides-Extra: horovod
Provides-Extra: nvtabular
Provides-Extra: dev
Provides-Extra: docs
Provides-Extra: tensorflow-dev
Provides-Extra: pytorch-dev
Provides-Extra: implicit-dev
Provides-Extra: lightfm-dev
Provides-Extra: xgboost-dev
Provides-Extra: all
License-File: LICENSE
